imagerie_lite/__init__.py
imagerie_lite/imagerie_lite.py
imagerie_lite/_lib/__init__.py
imagerie_lite/_lib/_util.py
imagerie_lite/_lib/six.py
imagerie_lite/ndimage/__init__.py
imagerie_lite/ndimage/_nd_image.py
imagerie_lite/ndimage/_ni_label.py
imagerie_lite/ndimage/_ni_support.py
imagerie_lite/operations/__init__.py
imagerie_lite/operations/distance.py
imagerie_lite/operations/img.py
imagerie_lite/operations/measurements.py
imagerie_lite/operations/morphology.py
imagerie_lite-0.0.8.dist-info/LICENSE
imagerie_lite-0.0.8.dist-info/METADATA
imagerie_lite-0.0.8.dist-info/WHEEL
imagerie_lite-0.0.8.dist-info/top_level.txt
imagerie_lite-0.0.8.dist-info/RECORD
