Metadata-Version: 2.1
Name: imagerie-lite
Version: 0.0.8
Summary: Python package grouping together common useful functions and operations.
Home-page: https://github.com/ibragim64/imagerie/tree/lite
Author: Ibragim Abubakarov
Author-email: ibragim.ai95@gmail.com
Maintainer: Ibragim Abubakarov
Maintainer-email: ibragim.ai95@gmail.com
License: UNKNOWN
Platform: UNKNOWN
Classifier: Programming Language :: Python :: 3
Classifier: Operating System :: OS Independent
Classifier: Intended Audience :: Developers
Classifier: Topic :: Software Development :: Libraries :: Python Modules
Classifier: Topic :: Multimedia
Requires-Dist: opencv-python
Requires-Dist: pillow
Requires-Dist: numpy
